pyvex/_register_info.py
pyvex/enums.py
pyvex/vex_ffi.py
pyvex/stmt.py
pyvex/__init__.py
pyvex/native.py
pyvex/types.py
pyvex/utils.py
pyvex/arches.py
pyvex/py.typed
pyvex/errors.py
pyvex/block.py
pyvex/data_ref.py
pyvex/const_val.py
pyvex/const.py
pyvex/expr.py
pyvex/include/libvex_guest_arm.h
pyvex/include/libvex_guest_ppc32.h
pyvex/include/libvex_guest_x86.h
pyvex/include/libvex_ir.h
pyvex/include/libvex_guest_arm64.h
pyvex/include/libvex_guest_riscv64.h
pyvex/include/libvex_guest_mips64.h
pyvex/include/libvex_emnote.h
pyvex/include/libvex_trc_values.h
pyvex/include/libvex_basictypes.h
pyvex/include/libvex.h
pyvex/include/libvex_guest_tilegx.h
pyvex/include/libvex_guest_ppc64.h
pyvex/include/libvex_guest_amd64.h
pyvex/include/libvex_guest_mips32.h
pyvex/include/libvex_guest_offsets.h
pyvex/include/libvex_s390x_common.h
pyvex/include/pyvex.h
pyvex/include/libvex_guest_s390x.h
pyvex/lib/libpyvex.dylib
pyvex/lifting/lifter.py
pyvex/lifting/post_processor.py
pyvex/lifting/__init__.py
pyvex/lifting/libvex.py
pyvex/lifting/zerodivision.py
pyvex/lifting/lift_function.py
pyvex/lifting/util/instr_helper.py
pyvex/lifting/util/lifter_helper.py
pyvex/lifting/util/__init__.py
pyvex/lifting/util/syntax_wrapper.py
pyvex/lifting/util/vex_helper.py
pyvex/lifting/gym/aarch64_spotter.py
pyvex/lifting/gym/arm_spotter.py
pyvex/lifting/gym/__init__.py
pyvex/lifting/gym/README.md
pyvex/lifting/gym/x86_spotter.py
pyvex-9.2.193.dist-info/RECORD
pyvex-9.2.193.dist-info/WHEEL
pyvex-9.2.193.dist-info/METADATA
pyvex-9.2.193.dist-info/licenses/LICENSE
pyvex-9.2.193.dist-info/licenses/pyvex_c/LICENSE
pyvex-9.2.193.dist-info/licenses/vex/LICENSE.GPL
pyvex-9.2.193.dist-info/licenses/vex/LICENSE.README
